instruction_decoder.sv
module instruction_decoder(I,CR,plar,plwr,sela,selw,plcr,plac,ena,inca,deca,resw,plwc,enw,incw,decw,oedata);
  input [2:0] I, CR;
  output reg plar,plwr,sela,selw,plcr,plac,ena,inca,deca,resw,plwc,enw,incw,decw,oedata;
  output reg [1:0] seld;
  
  always @(I or CR)
    casex({I,CR})
      6'b000_xxx : begin
        plar = 1'b0;
        plwr = 1'b0;
        sela = 1'bx;
        selw = 1'bx;
        plcr = 1'b1;
        seld = 2'bxx;
        plac = 1'b0;
        ena = 1'b0;
        inca = 1'b0;
        deca = 1'b0;
        resw = 1'b0;
        plwc = 1'b0;
        enw = 1'b0;
        incw = 1'b0;
        decw = 1'b0;
        oedata = 1'b0;
      end
      
      6'b001_xxx : begin
        plar = 1'b0;
        plwr = 1'b0;
        sela = 1'bx;
        selw = 1'bx;
        plcr = 1'b0;
        seld = 2'b1x;
        plac = 1'b0;
        ena = 1'b0;
        inca = 1'b0;
        deca = 1'b0;
        resw = 1'b0;
        plwc = 1'b0;
        enw = 1'b0;
        incw = 1'b0;
        decw = 1'b0;
        oedata = 1'b1;
      end
      
      6'b010_xxx : begin
        plar = 1'b0;
        plwr = 1'b0;
        sela = 1'bx;
        selw = 1'bx;
        plcr = 1'b0;
        seld = 2'b01;
        plac = 1'b0;
        ena = 1'b0;
        inca = 1'b0;
        deca = 1'b0;
        resw = 1'b0;
        plwc = 1'b0;
        enw = 1'b0;
        incw = 1'b0;
        decw = 1'b0;
        oedata = 1'b1;
      end
      
      6'b011_xxx : begin
        plar = 1'b0;
        plwr = 1'b0;
        sela = 1'bx;
        selw = 1'bx;
        plcr = 1'b0;
        seld = 2'b00;
        plac = 1'b0;
        ena = 1'b0;
        inca = 1'b0;
        deca = 1'b0;
        resw = 1'b0;
        plwc = 1'b0;
        enw = 1'b0;
        incw = 1'b0;
        decw = 1'b0;
        oedata = 1'b1;
      end
      
      6'b100_xx0 , 6'b100_x11 : begin
        plar = 1'b0;
        plwr = 1'b0;
        sela = 1'b1;
        selw = 1'b1;
        plcr = 1'b0;
        seld = 2'bxx;
        plac = 1'b1;
        ena = 1'b0;
        inca = 1'b0;
        deca = 1'b0;
        resw = 1'b0;
        plwc = 1'b1;
        enw = 1'b0;
        incw = 1'b0;
        decw = 1'b0;
        oedata = 1'b0;
      end
      
      6'b100_x01 : begin
        plar = 1'b0;
        plwr = 1'b0;
        sela = 1'b1;
        selw = 1'bx;
        plcr = 1'b0;
        seld = 2'bxx;
        plac = 1'b1;
        ena = 1'b0;
        inca = 1'b0;
        deca = 1'b0;
        resw = 1'b1;
        plwc = 1'b0;
        enw = 1'b0;
        incw = 1'b0;
        decw = 1'b0;
        oedata = 1'b0;
      end
      
      6'b101_xxx : begin
        plar = 1'b1;
        plwr = 1'b0;
        sela = 1'b0;
        selw = 1'bx;
        plcr = 1'b0;
        seld = 2'bxx;
        plac = 1'b1;
        ena = 1'b0;
        inca = 1'b0;
        deca = 1'b0;
        resw = 1'b0;
        plwc = 1'b0;
        enw = 1'b0;
        incw = 1'b0;
        decw = 1'b0;
        oedata = 1'b0;
      end
      
      6'b110_xx0 , 6'b110_x11 : begin
        plar = 1'b0;
        plwr = 1'b1;
        sela = 1'bx;
        selw = 1'b0;
        plcr = 1'b0;
        seld = 2'bxx;
        plac = 1'b0;
        ena = 1'b0;
        inca = 1'b0;
        deca = 1'b0;
        resw = 1'b0;
        plwc = 1'b1;
        enw = 1'b0;
        incw = 1'b0;
        decw = 1'b0;
        oedata = 1'b0;
      end
      
      6'b110_x01 : begin
        plar = 1'b0;
        plwr = 1'b1;
        sela = 1'bx;
        selw = 1'bx;
        plcr = 1'b0;
        seld = 2'bxx;
        plac = 1'b0;
        ena = 1'b0;
        inca = 1'b0;
        deca = 1'b0;
        resw = 1'b1;
        plwc = 1'b0;
        enw = 1'b0;
        incw = 1'b0;
        decw = 1'b0;
        oedata = 1'b0;
      end
      
      6'b111_000 : begin
        plar = 1'b0;
        plwr = 1'b0;
        sela = 1'bx;
        selw = 1'bx;
        plcr = 1'b0;
        seld = 2'bxx;
        plac = 1'b0;
        ena = 1'b1;
        inca = 1'b1;
        deca = 1'b0;
        resw = 1'b0;
        plwc = 1'b0;
        enw = 1'b1;
        incw = 1'b0;
        decw = 1'b1;
        oedata = 1'b0;
      end
      
      6'b111_0x1 : begin
        plar = 1'b0;
        plwr = 1'b0;
        sela = 1'bx;
        selw = 1'bx;
        plcr = 1'b0;
        seld = 2'bxx;
        plac = 1'b0;
        ena = 1'b1;
        inca = 1'b1;
        deca = 1'b0;
        resw = 1'b0;
        plwc = 1'b0;
        enw = 1'b1;
        incw = 1'b1;
        decw = 1'b0;
        oedata = 1'b0;
      end
      
      6'b111_010 : begin
        plar = 1'b0;
        plwr = 1'b0;
        sela = 1'bx;
        selw = 1'bx;
        plcr = 1'b0;
        seld = 2'bxx;
        plac = 1'b0;
        ena = 1'b1;
        inca = 1'b1;
        deca = 1'b0;
        resw = 1'b0;
        plwc = 1'b0;
        enw = 1'b0;
        incw = 1'b0;
        decw = 1'b0;
        oedata = 1'b0;
      end
      
      6'b111_100 : begin
        plar = 1'b0;
        plwr = 1'b0;
        sela = 1'bx;
        selw = 1'bx;
        plcr = 1'b0;
        seld = 2'bxx;
        plac = 1'b0;
        ena = 1'b1;
        inca = 1'b0;
        deca = 1'b1;
        resw = 1'b0;
        plwc = 1'b0;
        enw = 1'b1;
        incw = 1'b0;
        decw = 1'b1;
        oedata = 1'b0;
      end
      
      6'b111_1x1 : begin
        plar = 1'b0;
        plwr = 1'b0;
        sela = 1'bx;
        selw = 1'bx;
        plcr = 1'b0;
        seld = 2'bxx;
        plac = 1'b0;
        ena = 1'b1;
        inca = 1'b0;
        deca = 1'b1;
        resw = 1'b0;
        plwc = 1'b0;
        enw = 1'b1;
        incw = 1'b1;
        decw = 1'b0;
        oedata = 1'b0;
      end
      
      6'b111_1x1 : begin
        plar = 1'b0;
        plwr = 1'b0;
        sela = 1'bx;
        selw = 1'bx;
        plcr = 1'b0;
        seld = 2'bxx;
        plac = 1'b0;
        ena = 1'b1;
        inca = 1'b0;
        deca = 1'b1;
        resw = 1'b0;
        plwc = 1'b0;
        enw = 1'b0;
        incw = 1'b0;
        decw = 1'b0;
        oedata = 1'b0;
      end
    endcase
endmodule

mux1_3.sv
module mux1_3(clk,di0,di1,di2,dataout,seld);
  input clk;
  input [7:0] di0, di1;
  input [2:0] di2;
  output reg [7:0] dataout;
  input [1:0] seld;
    
  always @(di0 or di1 or di2 or seld)
      casex(seld)
        2'b00: dataout = di0;
        2'b01: dataout = di1;
        2'b1x: dataout = {5'b11111,di2};
      endcase
endmodule

done_gen.sv
module done_gen(doac, dowc, dowr, cinw, mode, done);
  input [7:0] doac, dowc, dowr;
  input [1:0] mode;
  input cinw;
  output reg done;
  
  always @(doac or dowc or dowr or cinw or mode)
    casex({mode,cinw})
      3'b00_0 : done = (dowc === 8'b1);
      3'b00_1 : done =~(dowc);
      3'b01_0 : done = (dowc + 1 === dowr);
      3'b01_1 : done = (dowc === dowr);
      3'b10_x : done = (dowc === doac);
      3'b11_x : done = 1'b0;
    endcase
endmodule

control_register.sv
module control_register(clk,plcr,din,dataout);
  input clk,plcr;
  input [2:0] din;
  output reg [2:0] dataout;
    
    always @(posedge clk)
      if(plcr)
        dataout <= din;
          
endmodule

counter.sv
module counter(clk,pl,reset,enc,inc,dec,cin,di,co,dataout);
  input clk,pl,enc,inc,dec,cin,reset;
  input [7:0] di;
  output co;
  output reg [7:0] dataout;
    
    always @(posedge clk)
     begin
      if(reset)
        dataout <= 8'b0;
  	  else
       if(pl)
        dataout <= di;
          else
            if(enc)
              if(inc && ~cin)
                begin
                  dataout <= dataout + 1;
                end
  				else
                  if(dec && ~cin)
                    begin
                      dataout <= dataout - 1;
                    end
  end
  
  assign co = (~((dataout===8'hff) && inc && enc)) && (~((dataout===8'h00) && dec && enc)) || cin;
                
endmodule

mux1_2.sv
module mux1_2(di0,di1,dataout,sel);
  input [7:0] di0,di1;
  input sel;
  output [7:0] dataout;
    
    assign dataout = sel ? di1 : di0;
      
endmodule

register.sv
module register(clk,pl,din,dataout);
  input clk,pl;
  input [7:0] din;
  output reg [7:0] dataout;
    
    always @(posedge clk)
      if(pl)
        dataout <= din;
          
endmodule

design.sv
// Code your design here
`include"register.sv"
`include"mux1_2.sv"
`include"counter.sv"
`include"control_register.sv"
`include"mux1_3.sv"
`include"done_gen.sv"
`include"instruction_decoder.sv"

module AM2940(clk, I, datain, dataout, addrout, done, aci, aco, wci, wco);
  input clk, aci, wci;
  input [2:0] I;
  input [7:0] datain;
  output [7:0] addrout;
  output [7:0] dataout;
  output wco, aco, done;
    
    //Semnale de comanda + variabile de transfer intre module(fire)
  wire plar,plwr,sela,selw,plcr,plac,ena,inca,deca,resw,plwc,enw,incw,decw,oedata;
  wire [1:0] seld; 
  wire [7:0] arout, wrout, addrmuxout, wordmuxout, acout, wcout;
  wire [2:0] crout;
    
  assign addrout = acout;
    
    //Registre
    //Registru adrese
  register address_register_inst(.clk(clk), .pl(plar), .din(datain), .dataout(arout));
    //Registru cuvinte
  register word_count_register_inst(.clk(clk), .pl(plwr), .din(datain), .dataout(wrout));
      
    //Multiplexor doua intrari - o iesire
    //Multiplexor adrese
  mux1_2 address_mux_inst(.di0(datain), .di1(arout), .dataout(addrmuxout), .sel(sela));
    //Multiplexor cuvinte
  mux1_2 word_count_mux_inst(.di0(datain), .di1(wrout), .dataout(wordmuxout), .sel(selw));
      
    //Numaratoare
    //Numarator adrese
    counter address_counter_inst(.clk(clk), .pl(plac), .reset(1'b0), .enc(ena), .inc(inca), .dec(deca), .cin(aci), .di(addrmuxout), .co(aco), .dataout(acout));
    //Numarator cuvinte
    counter word_count_counter_inst(.clk(clk), .pl(plac), .reset(resw), .enc(enw), .inc(incw), .dec(decw), .cin(wci), .di(wordmuxout), .co(wco), .dataout(wcout));
    
    //Registru Control
  control_register control_register_inst(.clk(clk), .plcr(plcr), .din(datain[2:0]), .dataout(crout));
      
    //Registru transfer de date complet
      done_gen done_gen_inst(.doac(acout), .dowc(wcout), .dowr(wrout), .cinw(wci), .mode(crout[1:0]), .done(done));
    
    //Multiplexor 3 intrari - o iesire
    //Multiplexor date
  mux1_3 datamux_inst(.clk(clk), .di0(acout), .di1(wcout), .di2(crout), .dataout(dataout), .seld(seld));
      
    //Decodor instructiuni
      instruction_decoder instruction_decoder_inst(.I(I), .CR(crout), .plar(plar), .plwr(plwr), .sela(sela), .selw(selw), .plcr(plcr), .plac(plac), .ena(ena), .inca(inca), .deca(deca), .resw(resw), .plwc(plwc), .enw(enw), .incw(incw), .decw(decw), .oedata(oedata));
      
endmodule

testbench.sv
// Code your testbench here
// or browse Examples
module tb_AM2940;
  reg clkt, acit, wcit;
  reg [2:0] It;
  reg [7:0] dataint;
  wire [7:0] dataoutt;
  wire [7:0] addroutt;
  wire acot,wcot,donet;
  AM2940 DUT(.clk(clkt), .I(It), .datain(dataint), .dataout(dataoutt), .addrout(addroutt), .done(donet), .aci(acit), .aco(acot), .wci(wcit), .wco(wcot));
  
  initial
    begin
      #0 clkt = 1'b0;
      forever #5 clkt = ~clkt;
    end

  initial
    begin
      #0 dataint=8'b1010_0011;
      //Instructiunea 0 : Write Control Register
      #5 dataint = 8'b110; It =3'b0;  acit = 1'b0; wcit = 1'b0;
      //Instructiunea 1 : Read Control Register
      #10 It = 3'b001;
      //Instructiunea 6 : Load Word Count
      #10 It = 3'b110; dataint = 8'haa;
      
      
      //Instructiunea 5 : Load Address
      #10 It = 3'b101;
      //Instructiunea 3 : Read Address Counter
      #10 It = 3'b011;
      //Instructiunea 0 : Write Control Register
      #10 It =3'b0; dataint = 8'b0;
      //Instructiunea 7 : Enable Counters
      #10 It = 3'b111;
      //Instructiunea 4 : Reinitialize Counters
      #10 It = 3'b100;
      //Instructiunea 3 : Read Address Counter
      #10 It = 3'b011;
      
      //Instructiunea 6 : Load Word Count
      #10 It = 3'b110;
      //Instructiunea 0 : Write Control Register
      #10 It =3'b0; dataint = 8'b1;
      //Instructiunea 6 : Load Word Count
      #10 It = 3'b110; dataint = 8'hbb;
      //Instructiunea 0 : Write Control Register
      #10 It =3'b0; dataint = 8'b1;
      //Instructiunea 4 : Reinitialize Counters
      #10 It = 3'b100;
      //Instructiunea 0 : Write Control Register
      #10 It =3'b0; dataint = 8'b0;
      //Instructiunea 4 : Reinitialize Counters
      #10 It = 3'b100;
      //Instructiunea 0 : Write Control Register
      #10 It =3'b0;

      
 /*   //Instructiunea 0 : Write Control Register
      #0 It =3'b0; dit = 8'b0; acit = 1'b0; wcit = 1'b0;
      //Instructiunea 1 : Read Control Register
      #10 It = 3'b001;
      //Instructiunea 5 : Load Address
      #10 It = 3'b101; dit = 8'b00001100;
      //Instructiunea 6 : Load Word Count
      #10 It = 3'b110; dit = 8'b00001000;
      //Instructiunea 2 : Read Word Counter
      #10 It = 3'b010;
      //Instructiunea 3 : Read Address Counter
      #10 It = 3'b011;
      //Instructiunea 7 : Enable Counters
      #10 It = 3'b111;
      
      //Instructiunea 0 : Write Control Register
      #40 It =3'b0; dit = 8'b00000111;
      //Instructiunea 4 : Reinitialize Counters
      #10 It = 3'b100;
      //Instructiunea 7 : Enable Counters
      #10 It = 3'b111;
      
      //Instructiunea 0 : Write Control Register
      #40 It =3'b0; dit = 8'b00000011;
      //Instructiunea 6 : Load Word Count
      #10 It = 3'b110; dit = 8'b00000011;
      //Instructiunea 5 : Load Address
      #10 It = 3'b101; dit = 8'hfe;
      //Instructiunea 7 : Enable Counters
      #10 It = 3'b111;
      
      //Instructiunea 6 : Load Word Count
      #10 It = 3'b110; dit = 8'hf0;
      //Instructiunea 0 : Write Control Register
      #40 It =3'b0; dit = 8'b0;
    */  
    end
  
    
  initial
    begin
      $dumpfile("dump.vcd");
      $dumpvars(0, DUT);
    end
  
  initial
    #500 $finish;
  
endmodule

dump.vcd
$date
	Mon Sep 19 16:31:50 2022
$end
$version
	Icarus Verilog
$end
$timescale
	1s
$end
$scope module tb_AM2940 $end
$scope module DUT $end
$var wire 3 ! I [2:0] $end
$var wire 1 " aci $end
$var wire 1 # aco $end
$var wire 8 $ acout [7:0] $end
$var wire 8 % addrmuxout [7:0] $end
$var wire 8 & addrout [7:0] $end
$var wire 8 ' arout [7:0] $end
$var wire 1 ( clk $end
$var wire 3 ) crout [2:0] $end
$var wire 8 * datain [7:0] $end
$var wire 8 + dataout [7:0] $end
$var wire 1 , deca $end
$var wire 1 - decw $end
$var wire 1 . done $end
$var wire 1 / ena $end
$var wire 1 0 enw $end
$var wire 1 1 inca $end
$var wire 1 2 incw $end
$var wire 1 3 oedata $end
$var wire 1 4 plac $end
$var wire 1 5 plar $end
$var wire 1 6 plcr $end
$var wire 1 7 plwc $end
$var wire 1 8 plwr $end
$var wire 1 9 resw $end
$var wire 1 : sela $end
$var wire 2 ; seld [1:0] $end
$var wire 1 < selw $end
$var wire 1 = wci $end
$var wire 1 > wco $end
$var wire 8 ? wcout [7:0] $end
$var wire 8 @ wordmuxout [7:0] $end
$var wire 8 A wrout [7:0] $end
$scope module address_register_inst $end
$var wire 1 ( clk $end
$var wire 8 B din [7:0] $end
$var wire 1 5 pl $end
$var reg 8 C dataout [7:0] $end
$upscope $end
$scope module word_count_register_inst $end
$var wire 1 ( clk $end
$var wire 8 D din [7:0] $end
$var wire 1 8 pl $end
$var reg 8 E dataout [7:0] $end
$upscope $end
$scope module address_mux_inst $end
$var wire 8 F dataout [7:0] $end
$var wire 8 G di0 [7:0] $end
$var wire 8 H di1 [7:0] $end
$var wire 1 : sel $end
$upscope $end
$scope module word_count_mux_inst $end
$var wire 8 I dataout [7:0] $end
$var wire 8 J di0 [7:0] $end
$var wire 8 K di1 [7:0] $end
$var wire 1 < sel $end
$upscope $end
$scope module address_counter_inst $end
$var wire 1 " cin $end
$var wire 1 ( clk $end
$var wire 1 # co $end
$var wire 1 , dec $end
$var wire 8 L di [7:0] $end
$var wire 1 / enc $end
$var wire 1 1 inc $end
$var wire 1 4 pl $end
$var wire 1 M reset $end
$var reg 8 N dataout [7:0] $end
$upscope $end
$scope module word_count_counter_inst $end
$var wire 1 = cin $end
$var wire 1 ( clk $end
$var wire 1 > co $end
$var wire 1 - dec $end
$var wire 8 O di [7:0] $end
$var wire 1 0 enc $end
$var wire 1 2 inc $end
$var wire 1 4 pl $end
$var wire 1 9 reset $end
$var reg 8 P dataout [7:0] $end
$upscope $end
$scope module control_register_inst $end
$var wire 1 ( clk $end
$var wire 3 Q din [2:0] $end
$var wire 1 6 plcr $end
$var reg 3 R dataout [2:0] $end
$upscope $end
$scope module done_gen_inst $end
$var wire 1 = cinw $end
$var wire 8 S doac [7:0] $end
$var wire 8 T dowc [7:0] $end
$var wire 8 U dowr [7:0] $end
$var wire 2 V mode [1:0] $end
$var reg 1 W done $end
$upscope $end
$scope module datamux_inst $end
$var wire 1 ( clk $end
$var wire 8 X di0 [7:0] $end
$var wire 8 Y di1 [7:0] $end
$var wire 3 Z di2 [2:0] $end
$var wire 2 [ seld [1:0] $end
$var reg 8 \ dataout [7:0] $end
$upscope $end
$scope module instruction_decoder_inst $end
$var wire 3 ] CR [2:0] $end
$var wire 3 ^ I [2:0] $end
$var reg 1 _ deca $end
$var reg 1 ` decw $end
$var reg 1 a ena $end
$var reg 1 b enw $end
$var reg 1 c inca $end
$var reg 1 d incw $end
$var reg 1 e oedata $end
$var reg 1 f plac $end
$var reg 1 g plar $end
$var reg 1 h plcr $end
$var reg 1 i plwc $end
$var reg 1 j plwr $end
$var reg 1 k resw $end
$var reg 1 l sela $end
$var reg 2 m seld [1:0] $end
$var reg 1 n selw $end
$upscope $end
$upscope $end
$upscope $end
$enddefinitions $end
#0
$dumpvars
xn
bx m
xl
xk
xj
xi
xh
xg
xf
xe
xd
xc
xb
xa
x`
x_
bx ^
bx ]
bx \
bz [
bx Z
bx Y
bx X
0W
bx V
bx U
bx T
bx S
bx R
b11 Q
bx P
bx O
bx N
0M
bx L
bx K
b10100011 J
bx I
bx H
b10100011 G
bx F
bx E
b10100011 D
bx C
b10100011 B
bx A
bx @
bx ?
1>
x=
x<
bz ;
x:
x9
x8
x7
x6
x5
x4
x3
x2
x1
x0
x/
0.
x-
x,
bx +
b10100011 *
bx )
0(
bx '
bx &
bx %
bx $
1#
x"
bx !
$end
#5
0e
03
0`
0-
0d
02
0b
00
0i
07
0k
09
0_
0,
0c
01
0a
0/
0f
04
1h
16
0j
08
0g
05
b110 Q
0=
0"
b0 !
b0 ^
b110 *
b110 B
b110 D
b110 G
b110 J
1(
#10
0(
#15
1e
13
b1x m
0h
06
1(
b1 !
b1 ^
#20
0(
#25
b10101010 E
b10101010 A
b10101010 K
b10101010 U
b10 Q
b10101010 @
b10101010 I
b10101010 O
0e
03
1i
17
bx m
0n
0<
1j
18
1(
b10101010 *
b10101010 B
b10101010 D
b10101010 G
b10101010 J
b110 !
b110 ^
#30
0(
#35
b10101010 P
b10101010 ?
b10101010 T
b10101010 Y
b10101010 C
b10101010 '
b10101010 H
b10101010 %
b10101010 F
b10101010 L
0i
07
1f
14
xn
x<
0l
0:
0j
08
1g
15
1(
b101 !
b101 ^
#40
0(
#45
1e
13
0f
04
b0 m
xl
x:
0g
05
1(
b11 !
b11 ^
#50
0(
#55
b0 V
b0 R
b0 )
b0 Z
b0 ]
b0 Q
bx0x0x0x0 %
bx0x0x0x0 F
bx0x0x0x0 L
bx0x0x0x0 @
bx0x0x0x0 I
bx0x0x0x0 O
0e
03
bx m
1h
16
1(
b0 *
b0 B
b0 D
b0 G
b0 J
b0 !
b0 ^
#60
0(
#65
b10101001 P
b10101001 ?
b10101001 T
b10101001 Y
1`
1-
1b
10
1c
11
1a
1/
0h
06
1(
b111 !
b111 ^
#70
0(
#75
bx0x0x0x0 \
bx0x0x0x0 +
bx0x0x0x0 P
bx0x0x0x0 ?
bx0x0x0x0 T
bx0x0x0x0 Y
bx0x0x0x0 N
bx0x0x0x0 $
bx0x0x0x0 S
bx0x0x0x0 X
bx0x0x0x0 &
b10101010 @
b10101010 I
b10101010 O
b10101010 %
b10101010 F
b10101010 L
0`
0-
0b
00
1i
17
0c
01
0a
0/
1f
14
1n
1<
1l
1:
1(
b100 !
b100 ^
#80
0(
#85
bx0x0x0x0 @
bx0x0x0x0 I
bx0x0x0x0 O
bx0x0x0x0 %
bx0x0x0x0 F
bx0x0x0x0 L
1e
13
0i
07
0f
04
b0 m
xn
x<
xl
x:
1(
b11 !
b11 ^
#90
0(
#95
b0 E
b0 A
b0 K
b0 U
b0 @
b0 I
b0 O
0e
03
1i
17
bx m
0n
0<
1j
18
1(
b110 !
b110 ^
#100
0(
#105
b1 V
b1 R
b1 )
b1 Z
b1 ]
b1 Q
bx0x0x0xx %
bx0x0x0xx F
bx0x0x0xx L
b0x @
b0x I
b0x O
0i
07
1h
16
xn
x<
0j
08
1(
b1 *
b1 B
b1 D
b1 G
b1 J
b0 !
b0 ^
#110
0(
#115
b0 P
b0 ?
b0 T
b0 Y
b10111011 E
b10111011 A
b10111011 K
b10111011 U
b11 Q
b101x101x %
b101x101x F
b101x101x L
b10111011 @
b10111011 I
b10111011 O
1k
19
0h
06
1j
18
1(
b10111011 *
b10111011 B
b10111011 D
b10111011 G
b10111011 J
b110 !
b110 ^
#120
0(
#125
b1 Q
bx0x0x0xx %
bx0x0x0xx F
bx0x0x0xx L
bx0xxx0x1 @
bx0xxx0x1 I
bx0xxx0x1 O
0k
09
1h
16
0j
08
1(
b1 *
b1 B
b1 D
b1 G
b1 J
b0 !
b0 ^
#130
0(
#135
bx0x0x0xx \
bx0x0x0xx +
bx0x0x0xx N
bx0x0x0xx $
bx0x0x0xx S
bx0x0x0xx X
bx0x0x0xx &
b10101010 %
b10101010 F
b10101010 L
1k
19
1f
14
0h
06
1l
1:
1(
b100 !
b100 ^
#140
0(
#145
b0 V
b0 R
b0 )
b0 Z
b0 ]
bx0x0x0x0 %
bx0x0x0x0 F
bx0x0x0x0 L
b0 Q
bx0xxx0xx @
bx0xxx0xx I
bx0xxx0xx O
0k
09
0f
04
1h
16
xl
x:
1(
b0 *
b0 B
b0 D
b0 G
b0 J
b0 !
b0 ^
#150
0(
#155
bx0x0x0x0 \
bx0x0x0x0 +
bx0xxx0xx P
bx0xxx0xx ?
bx0xxx0xx T
bx0xxx0xx Y
bx0x0x0x0 N
bx0x0x0x0 $
bx0x0x0x0 S
bx0x0x0x0 X
bx0x0x0x0 &
b10111011 @
b10111011 I
b10111011 O
b10101010 %
b10101010 F
b10101010 L
1i
17
1f
14
0h
06
1n
1<
1l
1:
1(
b100 !
b100 ^
#160
0(
#165
bx0xxx0xx @
bx0xxx0xx I
bx0xxx0xx O
bx0x0x0x0 %
bx0x0x0x0 F
bx0x0x0x0 L
0i
07
0f
04
1h
16
xn
x<
xl
x:
1(
b0 !
b0 ^
